stack_package_aps_techinfo/__init__.py
stack_package_aps_techinfo/stack.py
apsstack-0.0.3.dist-info/LICENSE.txt
apsstack-0.0.3.dist-info/METADATA
apsstack-0.0.3.dist-info/WHEEL
apsstack-0.0.3.dist-info/top_level.txt
apsstack-0.0.3.dist-info/RECORD
